evenoroddtool/__init__.py
evenoroddtool/evenorodd.py
evenoroddchecker-1.0.0.dist-info/METADATA
evenoroddchecker-1.0.0.dist-info/WHEEL
evenoroddchecker-1.0.0.dist-info/top_level.txt
evenoroddchecker-1.0.0.dist-info/RECORD
